msticpy/__init__.py
msticpy/_version.py
msticpy/lazy_importer.py
msticpy/msticpyconfig.yaml
msticpy/analysis/__init__.py
msticpy/analysis/cluster_auditd.py
msticpy/analysis/code_cleanup.py
msticpy/analysis/eventcluster.py
msticpy/analysis/observationlist.py
msticpy/analysis/outliers.py
msticpy/analysis/polling_detection.py
msticpy/analysis/syslog_utils.py
msticpy/analysis/timeseries.py
msticpy/analysis/anomalous_sequence/__init__.py
msticpy/analysis/anomalous_sequence/anomalous.py
msticpy/analysis/anomalous_sequence/model.py
msticpy/analysis/anomalous_sequence/sessionize.py
msticpy/analysis/anomalous_sequence/utils/__init__.py
msticpy/analysis/anomalous_sequence/utils/cmds_only.py
msticpy/analysis/anomalous_sequence/utils/cmds_params_only.py
msticpy/analysis/anomalous_sequence/utils/cmds_params_values.py
msticpy/analysis/anomalous_sequence/utils/data_structures.py
msticpy/analysis/anomalous_sequence/utils/laplace_smooth.py
msticpy/analysis/anomalous_sequence/utils/probabilities.py
msticpy/auth/__init__.py
msticpy/auth/azure_auth.py
msticpy/auth/azure_auth_core.py
msticpy/auth/cloud_mappings.py
msticpy/auth/cloud_mappings_offline.py
msticpy/auth/cred_wrapper.py
msticpy/auth/keyring_client.py
msticpy/auth/keyvault_client.py
msticpy/auth/keyvault_settings.py
msticpy/auth/msal_auth.py
msticpy/auth/secret_settings.py
msticpy/common/__init__.py
msticpy/common/azure_auth.py
msticpy/common/check_version.py
msticpy/common/data_types.py
msticpy/common/data_utils.py
msticpy/common/exceptions.py
msticpy/common/pkg_config.py
msticpy/common/provider_settings.py
msticpy/common/proxy_settings.py
msticpy/common/settings.py
msticpy/common/timespan.py
msticpy/common/wsconfig.py
msticpy/common/utility/__init__.py
msticpy/common/utility/format.py
msticpy/common/utility/ipython.py
msticpy/common/utility/package.py
msticpy/common/utility/types.py
msticpy/config/__init__.py
msticpy/config/ce_azure.py
msticpy/config/ce_azure_sentinel.py
msticpy/config/ce_common.py
msticpy-2.18.0.dist-info/licenses/LICENSE
msticpy-2.18.0.dist-info/licenses/NOTICE.txt
msticpy-2.18.0.dist-info/METADATA
msticpy-2.18.0.dist-info/WHEEL
msticpy-2.18.0.dist-info/top_level.txt
msticpy-2.18.0.dist-info/RECORD
