Metadata-Version: 2.4
Name: msticpy
Version: 2.18.0
Summary: MSTIC Security Tools
Home-page: https://github.com/microsoft/msticpy
Author: Ian Hellen
Author-email: ianhelle@microsoft.com
Maintainer: Pete Bryan
Maintainer-email: peter.bryan@microsoft.com
License: MIT License
Project-URL: Documentation, https://msticpy.readthedocs.io
Project-URL: Code, https://github.com/microsoft/msticpy
Project-URL: Issue tracker, https://github.com/microsoft/msticpy/issues
Keywords: security,azure,sentinel,mstic,cybersec,infosec,cyber,cybersecurity,jupyter,notebooks,SOC,hunting
Classifier: Programming Language :: Python
Classifier: Programming Language :: Python :: 3
Classifier: Programming Language :: Python :: 3 :: Only
Classifier: Programming Language :: Python :: 3.8
Classifier: Programming Language :: Python :: 3.9
Classifier: Programming Language :: Python :: 3.10
Classifier: Programming Language :: Python :: 3.11
Classifier: Programming Language :: Python :: 3.12
Classifier: License :: OSI Approved :: MIT License
Classifier: Operating System :: OS Independent
Classifier: Development Status :: 5 - Production/Stable
Classifier: Framework :: IPython
Classifier: Framework :: Jupyter
Classifier: Intended Audience :: Developers
Classifier: Intended Audience :: Information Technology
Classifier: Topic :: Security
Classifier: Topic :: Software Development :: Libraries :: Python Modules
Requires-Python: >=3.8
License-File: LICENSE
License-File: NOTICE.txt
Requires-Dist: attrs>=18.2.0
Requires-Dist: azure-common>=1.1.18
Requires-Dist: azure-core>=1.24.0
Requires-Dist: azure-identity>=1.16.1
Requires-Dist: azure-keyvault-secrets>=4.0.0
Requires-Dist: azure-kusto-data<=5.0.0,>=4.4.0
Requires-Dist: azure-mgmt-keyvault>=2.0.0
Requires-Dist: azure-mgmt-subscription>=3.0.0
Requires-Dist: azure-monitor-query<=2.0.0,>=1.0.0
Requires-Dist: beautifulsoup4>=4.0.0
Requires-Dist: bokeh>=3.0.0
Requires-Dist: cryptography>=43.0.1
Requires-Dist: deprecated>=1.2.4
Requires-Dist: dnspython<3.0.0,>=2.0.0
Requires-Dist: folium>=0.9.0
Requires-Dist: geoip2>=2.9.0
Requires-Dist: httpx<1.0.0,>=0.23.0
Requires-Dist: html5lib
Requires-Dist: importlib-resources>=6.4.0; python_version <= "3.8"
Requires-Dist: ipython>=7.1.1; python_version < "3.8"
Requires-Dist: ipython>=7.23.1; python_version >= "3.8"
Requires-Dist: ipywidgets<9.0.0,>=7.4.2
Requires-Dist: jinja2>=3.1.5
Requires-Dist: keyring>=13.2.1
Requires-Dist: lxml>=4.6.5
Requires-Dist: msal>=1.12.0
Requires-Dist: msal_extensions>=0.3.0
Requires-Dist: msrest>=0.6.0
Requires-Dist: msrestazure>=0.6.0
Requires-Dist: nest_asyncio>=1.4.0
Requires-Dist: networkx>=2.2
Requires-Dist: numpy>=1.15.4
Requires-Dist: packaging>=24.0
Requires-Dist: pandas<3.0.0,>=1.4.0
Requires-Dist: panel>=1.2.1
Requires-Dist: pydantic<3.0.0,>=1.8.0
Requires-Dist: pygments>=2.0.0
Requires-Dist: pyjwt>=2.3.0
Requires-Dist: python-dateutil>=2.8.1
Requires-Dist: pytz>=2019.2
Requires-Dist: pyyaml>=3.13
Requires-Dist: setuptools>=40.6.3
Requires-Dist: tldextract>=2.2.2
Requires-Dist: tornado>=6.4.2
Requires-Dist: tqdm>=4.36.1
Requires-Dist: typing-extensions>=4.2.0
Requires-Dist: urllib3>=1.23
Provides-Extra: dev
Requires-Dist: aiohttp>=3.7.4; extra == "dev"
Requires-Dist: async-cache>=1.1.1; extra == "dev"
Requires-Dist: bandit>=1.7.0; extra == "dev"
Requires-Dist: beautifulsoup4>=4.0.0; extra == "dev"
Requires-Dist: black<25.0.0,>=20.8b1; extra == "dev"
Requires-Dist: coverage>=5.5; extra == "dev"
Requires-Dist: docutils<0.22.0; extra == "dev"
Requires-Dist: filelock>=3.0.0; extra == "dev"
Requires-Dist: flake8>=3.8.4; extra == "dev"
Requires-Dist: httpx<0.28.0,>=0.23.0; extra == "dev"
Requires-Dist: isort>=5.10.1; extra == "dev"
Requires-Dist: jsonschema>=4.17.3; extra == "dev"
Requires-Dist: markdown>=3.3.4; extra == "dev"
Requires-Dist: mccabe>=0.6.1; extra == "dev"
Requires-Dist: mypy>=0.812; extra == "dev"
Requires-Dist: nbdime>=2.1.0; extra == "dev"
Requires-Dist: nbconvert>=6.1.0; extra == "dev"
Requires-Dist: pandas<3.0.0,>=1.4.0; extra == "dev"
Requires-Dist: pep8-naming>=0.10.0; extra == "dev"
Requires-Dist: pep8>=1.7.1; extra == "dev"
Requires-Dist: pipreqs>=0.4.9; extra == "dev"
Requires-Dist: pre-commit>=2.7.1; extra == "dev"
Requires-Dist: pycodestyle>=2.6.0; extra == "dev"
Requires-Dist: pydocstyle>=6.0.0; extra == "dev"
Requires-Dist: pyflakes>=2.2.0; extra == "dev"
Requires-Dist: pygeohash>=1.2.0; extra == "dev"
Requires-Dist: pylint>=2.5.3; extra == "dev"
Requires-Dist: pyroma>=3.1; extra == "dev"
Requires-Dist: pytest-check>=1.0.1; extra == "dev"
Requires-Dist: pytest-cov>=2.11.1; extra == "dev"
Requires-Dist: pytest-env>=1.1.0; extra == "dev"
Requires-Dist: pytest-xdist>=2.5.0; extra == "dev"
Requires-Dist: pytest>=5.0.1; extra == "dev"
Requires-Dist: readthedocs-sphinx-ext==2.2.5; extra == "dev"
Requires-Dist: responses>=0.13.2; extra == "dev"
Requires-Dist: respx>=0.20.1; extra == "dev"
Requires-Dist: ruff>=0.6.6; extra == "dev"
Requires-Dist: sphinx-rtd-theme>=1.0.0; extra == "dev"
Requires-Dist: sphinx<8.0.0,>=5.0.1; extra == "dev"
Requires-Dist: types-attrs>=19.0.0; extra == "dev"
Requires-Dist: types-requests>=2.32.0; extra == "dev"
Provides-Extra: vt3
Requires-Dist: vt-py>=0.18.0; extra == "vt3"
Requires-Dist: vt-graph-api>=2.0; extra == "vt3"
Provides-Extra: splunk
Requires-Dist: splunk-sdk!=2.0.0,>=1.6.0; extra == "splunk"
Provides-Extra: sumologic
Requires-Dist: sumologic-sdk>=0.1.11; extra == "sumologic"
Requires-Dist: openpyxl>=3.0; extra == "sumologic"
Provides-Extra: kql
Requires-Dist: KqlmagicCustom[jupyter-extended]>=0.1.114.post22; extra == "kql"
Provides-Extra: azure
Requires-Dist: azure-mgmt-compute>=4.6.2; extra == "azure"
Requires-Dist: azure-mgmt-core>=1.2.1; extra == "azure"
Requires-Dist: azure-mgmt-monitor>=2.0.0; extra == "azure"
Requires-Dist: azure-mgmt-network>=2.7.0; extra == "azure"
Requires-Dist: azure-mgmt-resource>=16.1.0; extra == "azure"
Requires-Dist: azure-storage-blob>=12.5.0; extra == "azure"
Requires-Dist: azure-mgmt-resourcegraph>=8.0.0; extra == "azure"
Provides-Extra: azure-query
Provides-Extra: keyvault
Provides-Extra: ml
Requires-Dist: scikit-learn>=1.0.0; extra == "ml"
Requires-Dist: scipy>=1.1.0; extra == "ml"
Requires-Dist: statsmodels>=0.11.1; extra == "ml"
Requires-Dist: matplotlib>=3.0.0; extra == "ml"
Requires-Dist: rrcf==0.4.4; extra == "ml"
Requires-Dist: joblib>=1.3.0; extra == "ml"
Provides-Extra: sql2kql
Requires-Dist: mo-sql-parsing<12.0.0,>=11; extra == "sql2kql"
Provides-Extra: riskiq
Requires-Dist: passivetotal>=2.5.3; extra == "riskiq"
Requires-Dist: requests>=2.31.0; extra == "riskiq"
Provides-Extra: panel
Provides-Extra: all
Requires-Dist: KqlmagicCustom[jupyter-extended]>=0.1.114.post22; extra == "all"
Requires-Dist: azure-mgmt-compute>=4.6.2; extra == "all"
Requires-Dist: azure-mgmt-core>=1.2.1; extra == "all"
Requires-Dist: azure-mgmt-monitor>=2.0.0; extra == "all"
Requires-Dist: azure-mgmt-network>=2.7.0; extra == "all"
Requires-Dist: azure-mgmt-resource>=16.1.0; extra == "all"
Requires-Dist: azure-mgmt-resourcegraph>=8.0.0; extra == "all"
Requires-Dist: azure-storage-blob>=12.5.0; extra == "all"
Requires-Dist: joblib>=1.3.0; extra == "all"
Requires-Dist: matplotlib>=3.0.0; extra == "all"
Requires-Dist: mo-sql-parsing<12.0.0,>=11; extra == "all"
Requires-Dist: openpyxl>=3.0; extra == "all"
Requires-Dist: passivetotal>=2.5.3; extra == "all"
Requires-Dist: requests>=2.31.0; extra == "all"
Requires-Dist: rrcf==0.4.4; extra == "all"
Requires-Dist: scikit-learn>=1.0.0; extra == "all"
Requires-Dist: scipy>=1.1.0; extra == "all"
Requires-Dist: splunk-sdk!=2.0.0,>=1.6.0; extra == "all"
Requires-Dist: statsmodels>=0.11.1; extra == "all"
Requires-Dist: sumologic-sdk>=0.1.11; extra == "all"
Requires-Dist: vt-graph-api>=2.0; extra == "all"
Requires-Dist: vt-py>=0.18.0; extra == "all"
Provides-Extra: test
Requires-Dist: KqlmagicCustom[jupyter-extended]>=0.1.114.post22; extra == "test"
Requires-Dist: aiohttp>=3.7.4; extra == "test"
Requires-Dist: async-cache>=1.1.1; extra == "test"
Requires-Dist: azure-mgmt-compute>=4.6.2; extra == "test"
Requires-Dist: azure-mgmt-core>=1.2.1; extra == "test"
Requires-Dist: azure-mgmt-monitor>=2.0.0; extra == "test"
Requires-Dist: azure-mgmt-network>=2.7.0; extra == "test"
Requires-Dist: azure-mgmt-resource>=16.1.0; extra == "test"
Requires-Dist: azure-mgmt-resourcegraph>=8.0.0; extra == "test"
Requires-Dist: azure-storage-blob>=12.5.0; extra == "test"
Requires-Dist: bandit>=1.7.0; extra == "test"
Requires-Dist: beautifulsoup4>=4.0.0; extra == "test"
Requires-Dist: black<25.0.0,>=20.8b1; extra == "test"
Requires-Dist: coverage>=5.5; extra == "test"
Requires-Dist: docutils<0.22.0; extra == "test"
Requires-Dist: filelock>=3.0.0; extra == "test"
Requires-Dist: flake8>=3.8.4; extra == "test"
Requires-Dist: httpx<0.28.0,>=0.23.0; extra == "test"
Requires-Dist: isort>=5.10.1; extra == "test"
Requires-Dist: joblib>=1.3.0; extra == "test"
Requires-Dist: jsonschema>=4.17.3; extra == "test"
Requires-Dist: markdown>=3.3.4; extra == "test"
Requires-Dist: matplotlib>=3.0.0; extra == "test"
Requires-Dist: mccabe>=0.6.1; extra == "test"
Requires-Dist: mo-sql-parsing<12.0.0,>=11; extra == "test"
Requires-Dist: mypy>=0.812; extra == "test"
Requires-Dist: nbconvert>=6.1.0; extra == "test"
Requires-Dist: nbdime>=2.1.0; extra == "test"
Requires-Dist: openpyxl>=3.0; extra == "test"
Requires-Dist: pandas<3.0.0,>=1.4.0; extra == "test"
Requires-Dist: passivetotal>=2.5.3; extra == "test"
Requires-Dist: pep8-naming>=0.10.0; extra == "test"
Requires-Dist: pep8>=1.7.1; extra == "test"
Requires-Dist: pipreqs>=0.4.9; extra == "test"
Requires-Dist: pre-commit>=2.7.1; extra == "test"
Requires-Dist: pycodestyle>=2.6.0; extra == "test"
Requires-Dist: pydocstyle>=6.0.0; extra == "test"
Requires-Dist: pyflakes>=2.2.0; extra == "test"
Requires-Dist: pygeohash>=1.2.0; extra == "test"
Requires-Dist: pylint>=2.5.3; extra == "test"
Requires-Dist: pyroma>=3.1; extra == "test"
Requires-Dist: pytest-check>=1.0.1; extra == "test"
Requires-Dist: pytest-cov>=2.11.1; extra == "test"
Requires-Dist: pytest-env>=1.1.0; extra == "test"
Requires-Dist: pytest-xdist>=2.5.0; extra == "test"
Requires-Dist: pytest>=5.0.1; extra == "test"
Requires-Dist: readthedocs-sphinx-ext==2.2.5; extra == "test"
Requires-Dist: requests>=2.31.0; extra == "test"
Requires-Dist: responses>=0.13.2; extra == "test"
Requires-Dist: respx>=0.20.1; extra == "test"
Requires-Dist: rrcf==0.4.4; extra == "test"
Requires-Dist: ruff>=0.6.6; extra == "test"
Requires-Dist: scikit-learn>=1.0.0; extra == "test"
Requires-Dist: scipy>=1.1.0; extra == "test"
Requires-Dist: sphinx-rtd-theme>=1.0.0; extra == "test"
Requires-Dist: sphinx<8.0.0,>=5.0.1; extra == "test"
Requires-Dist: splunk-sdk!=2.0.0,>=1.6.0; extra == "test"
Requires-Dist: statsmodels>=0.11.1; extra == "test"
Requires-Dist: sumologic-sdk>=0.1.11; extra == "test"
Requires-Dist: types-attrs>=19.0.0; extra == "test"
Requires-Dist: types-requests>=2.32.0; extra == "test"
Requires-Dist: vt-graph-api>=2.0; extra == "test"
Requires-Dist: vt-py>=0.18.0; extra == "test"
Provides-Extra: sentinel
Requires-Dist: azure-mgmt-compute>=4.6.2; extra == "sentinel"
Requires-Dist: azure-mgmt-core>=1.2.1; extra == "sentinel"
Requires-Dist: azure-mgmt-monitor>=2.0.0; extra == "sentinel"
Requires-Dist: azure-mgmt-network>=2.7.0; extra == "sentinel"
Requires-Dist: azure-mgmt-resource>=16.1.0; extra == "sentinel"
Requires-Dist: azure-storage-blob>=12.5.0; extra == "sentinel"
Requires-Dist: azure-mgmt-resourcegraph>=8.0.0; extra == "sentinel"
Provides-Extra: azsentinel
Requires-Dist: azure-mgmt-compute>=4.6.2; extra == "azsentinel"
Requires-Dist: azure-mgmt-core>=1.2.1; extra == "azsentinel"
Requires-Dist: azure-mgmt-monitor>=2.0.0; extra == "azsentinel"
Requires-Dist: azure-mgmt-network>=2.7.0; extra == "azsentinel"
Requires-Dist: azure-mgmt-resource>=16.1.0; extra == "azsentinel"
Requires-Dist: azure-storage-blob>=12.5.0; extra == "azsentinel"
Requires-Dist: azure-mgmt-resourcegraph>=8.0.0; extra == "azsentinel"
Provides-Extra: azuresentinel
Requires-Dist: azure-mgmt-compute>=4.6.2; extra == "azuresentinel"
Requires-Dist: azure-mgmt-core>=1.2.1; extra == "azuresentinel"
Requires-Dist: azure-mgmt-monitor>=2.0.0; extra == "azuresentinel"
Requires-Dist: azure-mgmt-network>=2.7.0; extra == "azuresentinel"
Requires-Dist: azure-mgmt-resource>=16.1.0; extra == "azuresentinel"
Requires-Dist: azure-storage-blob>=12.5.0; extra == "azuresentinel"
Requires-Dist: azure-mgmt-resourcegraph>=8.0.0; extra == "azuresentinel"
Dynamic: license-file
Dynamic: provides-extra
Dynamic: requires-dist
